autome/__init__.py
autome/automatas/__init__.py
autome/automatas/finite_automata/__init__.py
autome/automatas/finite_automata/machine.py
autome/automatas/finite_automata/parsers.py
autome/automatas/finite_automata/state.py
autome/automatas/finite_automata/transition.py
autome/automatas/turing_machine/machine.py
autome/automatas/turing_machine/parsers.py
autome/automatas/turing_machine/state.py
autome/automatas/turing_machine/tape.py
autome/automatas/turing_machine/transition.py
autome/base_machine.py
autome/grammars/__init__.py
autome/grammars/cfg.py
autome/regex/__init__.py
autome/regex/blocks/__init__.py
autome/regex/blocks/concat.py
autome/regex/blocks/epsilon.py
autome/regex/blocks/kleene.py
autome/regex/blocks/positive_closure.py
autome/regex/blocks/symbol.py
autome/regex/blocks/union.py
autome/regex/interpreter.py
autome/regex/lexer.py
autome/regex/nodes.py
autome/regex/parser.py
autome/regex/regex.py
autome/utils/__init__.py
autome/utils/dataclasses.py
autome/utils/enums.py
autome/utils/errors.py
autome/utils.py
autome-0.2.3.dist-info/WHEEL
autome-0.2.3.dist-info/METADATA
autome-0.2.3.dist-info/RECORD
