Metadata-Version: 2.1
Name: autome
Version: 0.2.3
Summary: Automata simulation with Python
Author: João Vitor Maia
Author-email: maia.tostring@gmail.com
Requires-Python: >=3.10,<4.0
Classifier: Programming Language :: Python :: 3
Classifier: Programming Language :: Python :: 3.10
Requires-Dist: black (>=22.3.0,<23.0.0)
Requires-Dist: click (>=8.1.3,<9.0.0)
Requires-Dist: ksuid (>=1.3,<2.0)
Requires-Dist: tabulate (>=0.8.9,<0.9.0)
